option_trader/__init__.py
option_trader/.vscode/launch.json
option_trader/.vscode/settings.json
option_trader/admin/account.py
option_trader/admin/site.py
option_trader/admin/user.py
option_trader/admin/tests/__init__.py
option_trader/admin/tests/test_admin.py
option_trader/backtest/option/butterfly.py
option_trader/backtest/option/credit_iron_condor.py
option_trader/backtest/option/single_option.py
option_trader/backtest/option/spread.py
option_trader/backtest/option/strategy.py
option_trader/backtest/stock/bollingerBands.py
option_trader/backtest/stock/macd.py
option_trader/backtest/stock/mfi.py
option_trader/backtest/stock/rsi.py
option_trader/consts/asset.py
option_trader/consts/predictor.py
option_trader/consts/rgb.py
option_trader/consts/strategy.py
option_trader/entity/monitor.py
option_trader/entity/position.py
option_trader/entity/position_summary.py
option_trader/entity/quote.py
option_trader/entity/top_pick.py
option_trader/entity/transaction.py
option_trader/jobs/account.py
option_trader/jobs/core.py
option_trader/jobs/site.py
option_trader/jobs/user.py
option_trader/settings/app_settings.py
option_trader/settings/ib_settings.py
option_trader/settings/log_config.py
option_trader/settings/logging.conf
option_trader/settings/schema.py
option_trader/settings/ta_strategy.py
option_trader/settings/trade_config.py
option_trader/shell/analyzer.py
option_trader/shell/backtester.py
option_trader/shell/dataset_tool.py
option_trader/shell/line.py
option_trader/tools/fidelity_reader.py
option_trader/tools/mail_processor.py
option_trader/tools/trade_factory.py
option_trader/utils/calc_prob.py
option_trader/utils/data_getter.py
option_trader/utils/data_getter_ib.py
option_trader/utils/gmail_notify.py
option_trader/utils/line_norify.py
option_trader/utils/option_tool.py
option_trader/utils/predictor.py
option_trader-0.2.74.dist-info/METADATA
option_trader-0.2.74.dist-info/WHEEL
option_trader-0.2.74.dist-info/licenses/LICENSE
option_trader-0.2.74.dist-info/RECORD
