Metadata-Version: 2.1
Name: option_trader
Version: 0.2.74
Summary: Option Trading Robot package
Project-URL: Homepage, https://github.com/pypa/OptionTradeproject
Project-URL: Bug Tracker, https://github.com/pypa/OptionTrader/issues
Author-email: Jim Huang <jim.huang.taipei@outlook.com>
License-File: LICENSE
Classifier: License :: OSI Approved :: MIT License
Classifier: Operating System :: OS Independent
Classifier: Programming Language :: Python :: 3
Requires-Python: >=3.7
